setup.cfg
setup.py
pyaem/__init__.py
pyaem/bagofrequests.py
pyaem/contentrepo.py
pyaem/exception.py
pyaem/handlers.py
pyaem/packagemanager.py
pyaem/packagemanagersync.py
pyaem/pyaem.py
pyaem/result.py
pyaem/webconsole.py
pyaem.egg-info/PKG-INFO
pyaem.egg-info/SOURCES.txt
pyaem.egg-info/dependency_links.txt
pyaem.egg-info/requires.txt
pyaem.egg-info/top_level.txt
test/test_bagofrequests.py
test/test_contentrepo.py
test/test_exception.py
test/test_handlers.py
test/test_packagemanager.py
test/test_packagemanagersync.py
test/test_pyaem.py
test/test_result.py
test/test_webconsole.py