Metadata-Version: 1.1
Name: pyaem
Version: 0.9.0
Summary: Python client for Adobe Experience Manager (AEM) API
Home-page: http://github.com/cliffano/pyaem/
Author: Cliffano Subagio
Author-email: cliffano@gmail.com
License: MIT License
Platform: any
Classifier: Programming Language :: Python
Classifier: Development Status :: 4 - Beta
Classifier: Natural Language :: English
Classifier: Intended Audience :: Developers
Classifier: License :: OSI Approved :: MIT License
Classifier: Operating System :: OS Independent
Classifier: Topic :: Software Development :: Libraries :: Python Modules
Classifier: Topic :: Internet :: WWW/HTTP :: Dynamic Content
